linkheader_parser/__init__.py
linkheader_parser/parser.py
linkheader_parser-0.6.dist-info/LICENSE
linkheader_parser-0.6.dist-info/METADATA
linkheader_parser-0.6.dist-info/WHEEL
linkheader_parser-0.6.dist-info/top_level.txt
linkheader_parser-0.6.dist-info/RECORD
