Metadata-Version: 2.1
Name: linkheader-parser
Version: 0.6
Summary: Python parser for LinkHeader
Home-page: https://github.com/FlorianLouvetRN/linkheader_parser
Author: Florian Louvet
License: Apache License 2.0
Keywords: link header parser python linkheader
Platform: UNKNOWN
Classifier: Development Status :: 5 - Production/Stable
Classifier: License :: OSI Approved :: Apache Software License
Classifier: Programming Language :: Python :: 3.5
Classifier: Programming Language :: Python :: 3.6
Classifier: Programming Language :: Python :: 3.7
Classifier: Programming Language :: Python :: 3 :: Only
Classifier: Topic :: Internet :: WWW/HTTP
